Metadata-Version: 2.4
Name: eastwind
Version: 2.3.0b6
Summary: A general-purpose automated research data processing framework
Project-URL: Homepage, https://autosoftint.com
Project-URL: Documentation, https://autosoftint.com/developer/documentation/eastwind
Project-URL: Repository, https://autosoftint.com/git/talus/eastwind
Project-URL: Bug Tracker, https://autosoftint.com/git/talus/eastwind/issues
Author-email: "ASI Pty. Ltd." <asi.au@outlook.com>, Saki Tojo <tomguts@126.com>
Maintainer-email: "ASI Pty. Ltd." <asi.au@outlook.com>, Saki Tojo <tomguts@126.com>
License-Expression: LicenseRef-Proprietary
Classifier: Development Status :: 4 - Beta
Classifier: Intended Audience :: Developers
Classifier: Programming Language :: Python :: 3
Requires-Python: >=3.11
Requires-Dist: aiofiles
Requires-Dist: aiomysql
Requires-Dist: aiosqlite
Requires-Dist: apscheduler
Requires-Dist: asyncpg
Requires-Dist: cryptography
Requires-Dist: fastapi
Requires-Dist: pydantic
Requires-Dist: pyyaml
Requires-Dist: sqlalchemy[asyncio]
Requires-Dist: tzdata
Requires-Dist: uuid6
Requires-Dist: uvicorn
Requires-Dist: websockets
